Controller_v2/controller_v2.v
module controller(
	output Lack,
	output Rreq,
	output LEreq,
	output REack,
	output clk,
	output sample,
	input Lreq,
	input Rack,
	input LEack,
	input REreq,
	input Err1,
	input Err0,
	input rst
);


	//Delta delay
	wire a, b;						
	
	//internal signals
	wire goLR, goME, goML, goEM, goLM, done ;

	assign #1 Lack = goML ;
	assign #1 Rreq = goLR ; 
	assign #1 LEreq = Lreq ;
	assign #1 REack = goME ;
	assign #1 clk = ~goLM & ~done & ~Err1 & ~Err0 & goME | goLM & done & ~Err1 & ~Err0 & ~goME ;
	assign #1 sample = ~goEM & ~a & ~b & goME | goEM & ~a & ~b & ~goME ;

	assign #1 goEM = REreq ;
	assign #1 done = ~Rack ;
	assign #1 goLR = LEack ;
	assign #1 goLM = LEack ;
	assign #1 goML = goEM & Err1 | goEM & Err0 | ~sample & goML & rst | ~Err1 & ~Err0 & goME ;	
	assign #1 goME = a & goML | b & goML | goML & goME & rst | ~a & ~b & goME & rst ;

	assign #1 a = Err0 ;
	assign #5 b = Err1;

	
endmodule

Controller_v2/tb_controller.v
module tb_controller();

   // simulation variables
   parameter hs_delay		  		= 5;
   parameter error_delay		  	= 7;
   parameter no_error_delay		  	= 2;

   parameter   reset_time           = 10;
   parameter   break_time		    = 500;
   parameter   step_time            = 1;
   integer     done                 = 0;
   integer     i                    = 1;

	wire Lack;
	wire Rreq;
	wire LEreq;
	wire REack;
	wire clk;
	wire sample;
	reg Lreq;
	reg Rack;
	reg LEack;
	reg REreq;
	reg Err1;
	reg Err0;
	reg rst;

	reg reseted;

	reg state;
    reg [1:0] cnt ;

	controller uut(
		.Lack(Lack),
		.Rreq(Rreq),
		.LEreq(LEreq),
		.REack(REack),
		.clk(clk),
		.sample(sample),
		.Lreq(Lreq),
		.Rack(Rack),
		.LEack(LEack),
		.REreq(REreq),
		.Err1(Err1),
		.Err0(Err0),
		.rst(rst)
 	);

 	initial begin

 		$dumpfile("tb_controller.vcd");
      	$dumpvars(0, tb_controller);

 		Lreq = 'b0;
		Rack = 'b0;
		LEack = 'b0;
		REreq = 'b0;
		Err1 = 'b0;
		Err0 = 'b0;
		rst = 'b0;
		
		state = 'b1;
		cnt = 'b0;
		#(reset_time);
 		rst = 'b1;

 		#2
 		Lreq = 'b1;
 		
		#(break_time);
		$finish;
 	end


 	//Here I need to simulate the pipeline environment
  	always @ (REack) begin 
 		if(rst)	#(hs_delay)	Rack = REack;
	end

	always @ (Lack) begin 
		if(rst)	#(hs_delay)	Lreq = ~Lack;
	end

	always @ (LEreq) begin 
 		if(rst)	#(hs_delay)	LEack = LEreq;
	end

	always @ (Rreq) begin 
 		if(rst)	#(hs_delay)	REreq = Rreq;
	end


	always @ (sample) begin 
		if(rst) begin
			if (state) begin 
				#2 Err0 = sample;
				if (~sample) begin
					cnt = cnt + 1;
					if(cnt > 1) begin
					 	state = 'b0 ;
					 	cnt = 0;
					end
				end
			end else begin
				#2 Err1 = sample;
				if (~sample) begin
					cnt = cnt + 1;
					if(cnt > 1) begin
					 	state = 'b1 ;
					 	cnt = 0;
					end
				end
			end
		end
	end

endmodule

Controller_v2/tb_controller.vcd
$date
	Wed Jun 18 16:02:14 2014
$end
$version
	Icarus Verilog
$end
$timescale
	1s
$end
$scope module tb_controller $end
$var wire 1 ! LEreq $end
$var wire 1 " Lack $end
$var wire 1 # REack $end
$var wire 1 $ Rreq $end
$var wire 1 % clk $end
$var wire 1 & sample $end
$var reg 1 ' Err0 $end
$var reg 1 ( Err1 $end
$var reg 1 ) LEack $end
$var reg 1 * Lreq $end
$var reg 1 + REreq $end
$var reg 1 , Rack $end
$var reg 2 - cnt [1:0] $end
$var integer 32 . done [31:0] $end
$var integer 32 / i [31:0] $end
$var reg 1 0 rst $end
$var reg 1 1 state $end
$scope module uut $end
$var wire 1 2 Err0 $end
$var wire 1 3 Err1 $end
$var wire 1 4 LEack $end
$var wire 1 ! LEreq $end
$var wire 1 " Lack $end
$var wire 1 5 Lreq $end
$var wire 1 # REack $end
$var wire 1 6 REreq $end
$var wire 1 7 Rack $end
$var wire 1 $ Rreq $end
$var wire 1 8 a $end
$var wire 1 9 b $end
$var wire 1 % clk $end
$var wire 1 : done $end
$var wire 1 ; goEM $end
$var wire 1 < goLM $end
$var wire 1 = goLR $end
$var wire 1 > goME $end
$var wire 1 ? goML $end
$var wire 1 @ rst $end
$var wire 1 & sample $end
$upscope $end
$upscope $end
$enddefinitions $end
#0
$dumpvars
0@
x?
x>
x=
x<
x;
z:
x9
x8
07
06
05
04
03
02
11
00
b1 /
b0 .
b0 -
0,
0+
0*
0)
0(
0'
x&
x%
x$
x#
x"
x!
$end
#1
1:
08
0;
0=
0<
0!
#2
0%
0$
#5
09
#6
0>
#7
0?
0&
0#
#8
0"
#10
10
1@
#12
1*
15
#13
1!
#18
1)
14
#19
1=
1<
#20
1%
1$
#25
1+
16
#26
1;
#27
1&
#29
1'
12
#30
0%
1?
18
#31
0&
1>
1"
#32
1#
#33
b1 -
0'
02
#34
08
#36
0*
05
#37
0!
1,
17
#38
0:
#42
0)
04
#43
0=
0<
#44
1%
0$
#49
0+
06
#50
0;
#51
1&
#53
1'
12
#54
0%
0?
18
#55
0&
0>
0"
#56
0#
#57
01
b0 -
0'
02
#58
08
#60
1*
15
#61
1!
0,
07
#62
1:
#66
1)
14
#67
1=
1<
#68
1%
1$
#73
1+
16
#74
1;
#75
1&
#77
1(
13
#78
0%
1?
#79
1"
#82
19
#83
1>
0&
#84
1#
0*
05
#85
0!
b1 -
0(
03
#89
1,
17
#90
0:
0)
04
09
#91
0=
0<
#92
1%
0$
#97
0+
06
#98
0;
#99
1&
#101
1(
13
#102
0%
0?
#103
0"
#106
19
#107
0>
0&
#108
0#
1*
15
#109
1!
11
b0 -
0(
03
#113
0,
07
#114
1:
1)
14
09
#115
1=
1<
#116
1%
1$
#121
1+
16
#122
1;
#123
1&
#125
1'
12
#126
0%
1?
18
#127
0&
1>
1"
#128
1#
#129
b1 -
0'
02
#130
08
#132
0*
05
#133
0!
1,
17
#134
0:
#138
0)
04
#139
0=
0<
#140
1%
0$
#145
0+
06
#146
0;
#147
1&
#149
1'
12
#150
0%
0?
18
#151
0&
0>
0"
#152
0#
#153
01
b0 -
0'
02
#154
08
#156
1*
15
#157
1!
0,
07
#158
1:
#162
1)
14
#163
1=
1<
#164
1%
1$
#169
1+
16
#170
1;
#171
1&
#173
1(
13
#174
0%
1?
#175
1"
#178
19
#179
1>
0&
#180
1#
0*
05
#181
0!
b1 -
0(
03
#185
1,
17
#186
0:
0)
04
09
#187
0=
0<
#188
1%
0$
#193
0+
06
#194
0;
#195
1&
#197
1(
13
#198
0%
0?
#199
0"
#202
19
#203
0>
0&
#204
0#
1*
15
#205
1!
11
b0 -
0(
03
#209
0,
07
#210
1:
1)
14
09
#211
1=
1<
#212
1%
1$
#217
1+
16
#218
1;
#219
1&
#221
1'
12
#222
0%
1?
18
#223
0&
1>
1"
#224
1#
#225
b1 -
0'
02
#226
08
#228
0*
05
#229
0!
1,
17
#230
0:
#234
0)
04
#235
0=
0<
#236
1%
0$
#241
0+
06
#242
0;
#243
1&
#245
1'
12
#246
0%
0?
18
#247
0&
0>
0"
#248
0#
#249
01
b0 -
0'
02
#250
08
#252
1*
15
#253
1!
0,
07
#254
1:
#258
1)
14
#259
1=
1<
#260
1%
1$
#265
1+
16
#266
1;
#267
1&
#269
1(
13
#270
0%
1?
#271
1"
#274
19
#275
1>
0&
#276
1#
0*
05
#277
0!
b1 -
0(
03
#281
1,
17
#282
0:
0)
04
09
#283
0=
0<
#284
1%
0$
#289
0+
06
#290
0;
#291
1&
#293
1(
13
#294
0%
0?
#295
0"
#298
19
#299
0>
0&
#300
0#
1*
15
#301
1!
11
b0 -
0(
03
#305
0,
07
#306
1:
1)
14
09
#307
1=
1<
#308
1%
1$
#313
1+
16
#314
1;
#315
1&
#317
1'
12
#318
0%
1?
18
#319
0&
1>
1"
#320
1#
#321
b1 -
0'
02
#322
08
#324
0*
05
#325
0!
1,
17
#326
0:
#330
0)
04
#331
0=
0<
#332
1%
0$
#337
0+
06
#338
0;
#339
1&
#341
1'
12
#342
0%
0?
18
#343
0&
0>
0"
#344
0#
#345
01
b0 -
0'
02
#346
08
#348
1*
15
#349
1!
0,
07
#350
1:
#354
1)
14
#355
1=
1<
#356
1%
1$
#361
1+
16
#362
1;
#363
1&
#365
1(
13
#366
0%
1?
#367
1"
#370
19
#371
1>
0&
#372
1#
0*
05
#373
0!
b1 -
0(
03
#377
1,
17
#378
0:
0)
04
09
#379
0=
0<
#380
1%
0$
#385
0+
06
#386
0;
#387
1&
#389
1(
13
#390
0%
0?
#391
0"
#394
19
#395
0>
0&
#396
0#
1*
15
#397
1!
11
b0 -
0(
03
#401
0,
07
#402
1:
1)
14
09
#403
1=
1<
#404
1%
1$
#409
1+
16
#410
1;
#411
1&
#413
1'
12
#414
0%
1?
18
#415
0&
1>
1"
#416
1#
#417
b1 -
0'
02
#418
08
#420
0*
05
#421
0!
1,
17
#422
0:
#426
0)
04
#427
0=
0<
#428
1%
0$
#433
0+
06
#434
0;
#435
1&
#437
1'
12
#438
0%
0?
18
#439
0&
0>
0"
#440
0#
#441
01
b0 -
0'
02
#442
08
#444
1*
15
#445
1!
0,
07
#446
1:
#450
1)
14
#451
1=
1<
#452
1%
1$
#457
1+
16
#458
1;
#459
1&
#461
1(
13
#462
0%
1?
#463
1"
#466
19
#467
1>
0&
#468
1#
0*
05
#469
0!
b1 -
0(
03
#473
1,
17
#474
0:
0)
04
09
#475
0=
0<
#476
1%
0$
#481
0+
06
#482
0;
#483
1&
#485
1(
13
#486
0%
0?
#487
0"
#490
19
#491
0>
0&
#492
0#
1*
15
#493
1!
11
b0 -
0(
03
#497
0,
07
#498
1:
1)
14
09
#499
1=
1<
#500
1%
1$
#505
1+
16
#506
1;
#507
1&
#509
1'
12
#510
0%
1?
18
#511
0&
1>
1"
#512
1#
