Controller_v2/controller_v2.v
module controller(
	output Lack,
	output Rreq,
	output LEreq,
	output REack,
	output clk,
	output sample,
	input Lreq,
	input Rack,
	input LEack,
	input REreq,
	input Err1,
	input Err0,
	input rst
);


	//Delta delay
	wire a, b;						
	
	//internal signals
	wire goML, goLM ;

	assign #1 Lack = goML ;
	assign #1 Rreq = goLM & ~Rack | goLM & Rreq | ~Rack & Rreq & rst ;
	assign #1 LEreq = Lreq ;
	assign #1 REack = goML & REack & rst | b & Rreq | a & Rreq | ~a & ~b & REack & rst ;
	assign #1 clk = ~goLM & Rack & ~Err1 & ~Err0 & REack | goLM & ~Rack & ~Err1 & ~Err0 & ~REack ;
	assign #1 sample = ~REreq & ~a & ~b & REack | REreq & ~a & ~b & ~REack ;

	assign #1 goLM = LEack ;
	assign #1 goML = ~sample & goML & rst | Err1 & Rreq | Err0 & Rreq | ~Err1 & ~Err0 & REack ;	

	assign #1 a = Err0 ;
	assign #15 b = Err1;

	
endmodule

Controller_v2/tb_controller.v
module tb_controller();

   // simulation variables
   parameter hs_delay		  		= 20;
   parameter error_delay		  	= 7;
   parameter no_error_delay		  	= 2;

   parameter   reset_time           = 10;
   parameter   break_time		    = 500;
   parameter   step_time            = 1;
   integer     done                 = 0;
   integer     i                    = 1;

	wire Lack;
	wire Rreq;
	wire LEreq;
	wire REack;
	wire clk;
	wire sample;
	reg Lreq;
	reg Rack;
	reg LEack;
	reg REreq;
	reg Err1;
	reg Err0;
	reg rst;

	reg reseted;

	reg state;
    reg [1:0] counter_error ;
    reg [1:0] counter_rack ;

	controller uut(
		.Lack(Lack),
		.Rreq(Rreq),
		.LEreq(LEreq),
		.REack(REack),
		.clk(clk),
		.sample(sample),
		.Lreq(Lreq),
		.Rack(Rack),
		.LEack(LEack),
		.REreq(REreq),
		.Err1(Err1),
		.Err0(Err0),
		.rst(rst)
 	);

 	initial begin

 		$dumpfile("tb_controller.vcd");
      	$dumpvars(0, tb_controller);

 		Lreq = 'b0;
		Rack = 'b0;
		LEack = 'b0;
		REreq = 'b0;
		Err1 = 'b0;
		Err0 = 'b0;
		rst = 'b0;
		
		state = 'b1;
		counter_error = 'b0;
		counter_rack = 'b0;
		#(reset_time);
 		rst = 'b1;

 		#2
 		Lreq = 'b1;
 		
		#(break_time);
		$finish;
 	end


 	//Here I need to simulate the pipeline environment

	//Lreq
	always @ (Lack) begin 
		if(rst)	#10	Lreq = ~Lack;
	end

	//LEack
	always @ (LEreq) begin 
 		if(rst)	#(hs_delay)	LEack = LEreq;
	end

	//REreq
	always @ (Rreq) begin 
 		if(rst)	#(hs_delay)	REreq = Rreq;
	end
  	
  	//Rack
  	always @ (REack) begin 
 		if(rst && counter_rack < 3) begin
			#(hs_delay)	Rack = REack;
			counter_rack = counter_rack + 1;
 		end else begin
 			#50 Rack = REack;
 			counter_rack = 'b0;
 		end
	end

	//Err0 and Err1
	always @ (sample) begin 
		if(rst) begin
			if (state) begin 
				#5 Err0 = sample;
				if (~sample) begin
					counter_error = counter_error + 1;
					if(counter_error > 1) begin
					 	state = 'b0 ;
					 	counter_error = 0;
					end
				end
			end else begin
				#5 Err1 = sample;
				if (~sample) begin
					counter_error = counter_error + 1;
					if(counter_error > 1) begin
					 	state = 'b1 ;
					 	counter_error = 0;
					end
				end
			end
		end
	end

endmodule

Controller_v2/tb_controller.vcd
$date
	Thu Jun 19 11:38:59 2014
$end
$version
	Icarus Verilog
$end
$timescale
	1s
$end
$scope module tb_controller $end
$var wire 1 ! LEreq $end
$var wire 1 " Lack $end
$var wire 1 # REack $end
$var wire 1 $ Rreq $end
$var wire 1 % clk $end
$var wire 1 & sample $end
$var reg 1 ' Err0 $end
$var reg 1 ( Err1 $end
$var reg 1 ) LEack $end
$var reg 1 * Lreq $end
$var reg 1 + REreq $end
$var reg 1 , Rack $end
$var reg 2 - counter_error [1:0] $end
$var reg 2 . counter_rack [1:0] $end
$var integer 32 / done [31:0] $end
$var integer 32 0 i [31:0] $end
$var reg 1 1 rst $end
$var reg 1 2 state $end
$scope module uut $end
$var wire 1 3 Err0 $end
$var wire 1 4 Err1 $end
$var wire 1 5 LEack $end
$var wire 1 ! LEreq $end
$var wire 1 " Lack $end
$var wire 1 6 Lreq $end
$var wire 1 # REack $end
$var wire 1 7 REreq $end
$var wire 1 8 Rack $end
$var wire 1 $ Rreq $end
$var wire 1 9 a $end
$var wire 1 : b $end
$var wire 1 % clk $end
$var wire 1 ; goLM $end
$var wire 1 < goML $end
$var wire 1 = rst $end
$var wire 1 & sample $end
$upscope $end
$upscope $end
$enddefinitions $end
#0
$dumpvars
0=
x<
x;
x:
x9
08
07
06
05
04
03
12
01
b1 0
b0 /
b0 .
b0 -
0,
0+
0*
0)
0(
0'
x&
x%
x$
x#
x"
x!
$end
#1
09
0;
0!
#2
0%
0$
#3
0#
#4
0&
0<
#5
0"
#10
11
1=
#12
1*
16
#13
1!
#15
0:
#33
1)
15
#34
1;
#35
1%
1$
#55
1+
17
#56
1&
#58
1'
13
#59
0%
1<
19
#60
0&
1#
1"
#61
0*
06
#62
0!
b1 -
0'
03
#63
09
#80
b1 .
1,
18
#82
0)
05
#83
0;
#84
1%
0$
#104
0+
07
#105
1&
#107
1'
13
#108
0%
0<
19
#109
0&
0#
0"
#110
1*
16
#111
1!
02
b0 -
0'
03
#112
09
#129
b10 .
0,
08
#131
1)
15
#132
1;
#133
1%
1$
#153
1+
17
#154
1&
#156
1(
14
#157
0%
1<
#158
1"
#159
0*
06
#160
0!
#171
1:
#172
0&
1#
#174
b1 -
0(
04
#180
0)
05
#181
0;
#189
0:
#192
b11 .
1,
18
#193
1%
0$
#213
0+
07
#214
1&
#216
1(
14
#217
0%
0<
#218
0"
#219
1*
16
#220
1!
#231
1:
#232
0#
0&
#234
12
b0 -
0(
04
#240
1)
15
#241
1;
#249
0:
