Controller_v2/controller_v2.v
module controller(
	output Lack,
	output Rreq,
	output LEreq,
	output REack,
	output clk,
	output sample,
	input Lreq,
	input Rack,
	input LEack,
	input REreq,
	input Err1,
	input Err0,
	input rst
);

	//Delta delay
	wire a, b;						
	
	//internal signals
	wire goML, goLM ;

	assign #1 Lack = goML ;
	assign #1 Rreq = goLM & ~Rack | goLM & Rreq | ~Rack & Rreq & rst ;
	assign #1 LEreq = Lreq ;
	assign #1 REack = goML & REack & rst | b & Rreq | a & Rreq | ~a & ~b & REack & rst ;
	assign #1 clk = ~goLM & Rack & ~Err1 & ~Err0 & REack | goLM & ~Rack & ~Err1 & ~Err0 & ~REack ;
	assign #1 sample = ~REreq & ~a & ~b & REack | REreq & ~a & ~b & ~REack ;

	assign #1 goLM = LEack ;
	assign #1 goML = ~sample & goML & rst | Err1 & Rreq | Err0 & Rreq | ~Err1 & ~Err0 & REack ;	

	assign #5 a = Err0 ;
	assign #15 b = Err1;

	
endmodule

Controller_v2/tb_controller.v
module tb_controller();

   // simulation variables
   parameter hs_delay		  		= 20;
   parameter error_delay		  	= 7;
   parameter no_error_delay		  	= 2;

   parameter   reset_time           = 10;
   parameter   break_time		    = 500;
   parameter   step_time            = 1;
   integer     done                 = 0;
   integer     i                    = 1;

	wire Lack;
	wire Rreq;
	wire LEreq;
	wire REack;
	wire clk;
	wire sample;
	reg Lreq;
	reg Rack;
	reg LEack;
	reg REreq;
	reg Err1;
	reg Err0;
	reg rst;

	reg reseted;

	reg state;
    reg [1:0] counter_error ;
    reg [1:0] counter_rack ;

	controller uut(
		.Lack(Lack),
		.Rreq(Rreq),
		.LEreq(LEreq),
		.REack(REack),
		.clk(clk),
		.sample(sample),
		.Lreq(Lreq),
		.Rack(Rack),
		.LEack(LEack),
		.REreq(REreq),
		.Err1(Err1),
		.Err0(Err0),
		.rst(rst)
 	);

 	initial begin

 		$dumpfile("tb_controller.vcd");
      	$dumpvars(0, tb_controller);

 		Lreq = 'b0;
		Rack = 'b0;
		LEack = 'b0;
		REreq = 'b0;
		Err1 = 'b0;
		Err0 = 'b0;
		rst = 'b0;
		
		state = 'b1;
		counter_error = 'b0;
		counter_rack = 'b0;
		#(reset_time);
 		rst = 'b1;

 		#2
 		Lreq = 'b1;
 		
		#(break_time);
		$finish;
 	end


 	//Here I need to simulate the pipeline environment

	//Lreq
	always @ (Lack) begin 
		if(rst)	#10	Lreq = ~Lack;
	end

	//LEack
	always @ (LEreq) begin 
 		if(rst)	#(hs_delay)	LEack = LEreq;
	end

	//REreq
	always @ (Rreq) begin 
 		if(rst)	#(hs_delay)	REreq = Rreq;
	end
  	
  	//Rack
  	always @ (REack) begin 
 		if(rst && counter_rack < 3) begin
			#(hs_delay)	Rack = REack;
			counter_rack = counter_rack + 1;
 		end else begin
 			#50 Rack = REack;
 			counter_rack = 'b0;
 		end
	end

	//Err0 and Err1
	always @ (sample) begin 
		if(rst) begin
			if (state) begin 
				#5 Err0 = sample;
				if (~sample) begin
					counter_error = counter_error + 1;
					if(counter_error > 1) begin
					 	state = 'b0 ;
					 	counter_error = 0;
					end
				end
			end else begin
				#5 Err1 = sample;
				if (~sample) begin
					counter_error = counter_error + 1;
					if(counter_error > 1) begin
					 	state = 'b1 ;
					 	counter_error = 0;
					end
				end
			end
		end
	end

endmodule

Controller_v2/tb_controller.vcd
$date
	Thu Jun 19 20:23:31 2014
$end
$version
	Icarus Verilog
$end
$timescale
	1s
$end
$scope module tb_controller $end
$var wire 1 ! LEreq $end
$var wire 1 " Lack $end
$var wire 1 # REack $end
$var wire 1 $ Rreq $end
$var wire 1 % clk $end
$var wire 1 & sample $end
$var reg 1 ' Err0 $end
$var reg 1 ( Err1 $end
$var reg 1 ) LEack $end
$var reg 1 * Lreq $end
$var reg 1 + REreq $end
$var reg 1 , Rack $end
$var reg 2 - counter_error [1:0] $end
$var reg 2 . counter_rack [1:0] $end
$var integer 32 / done [31:0] $end
$var integer 32 0 i [31:0] $end
$var reg 1 1 rst $end
$var reg 1 2 state $end
$scope module uut $end
$var wire 1 3 Err0 $end
$var wire 1 4 Err1 $end
$var wire 1 5 LEack $end
$var wire 1 ! LEreq $end
$var wire 1 " Lack $end
$var wire 1 6 Lreq $end
$var wire 1 # REack $end
$var wire 1 7 REreq $end
$var wire 1 8 Rack $end
$var wire 1 $ Rreq $end
$var wire 1 9 a $end
$var wire 1 : b $end
$var wire 1 % clk $end
$var wire 1 ; goLM $end
$var wire 1 < goML $end
$var wire 1 = rst $end
$var wire 1 & sample $end
$upscope $end
$upscope $end
$enddefinitions $end
#0
$dumpvars
0=
x<
x;
x:
x9
08
07
06
05
04
03
12
01
b1 0
b0 /
b0 .
b0 -
0,
0+
0*
0)
0(
0'
x&
x%
x$
x#
x"
x!
$end
#1
0;
0!
#2
0%
0$
#3
0#
#4
0&
0<
#5
0"
09
#10
11
1=
#12
1*
16
#13
1!
#15
0:
#33
1)
15
#34
1;
#35
1%
1$
#55
1+
17
#56
1&
#61
1'
13
#62
0%
1<
#63
1"
#66
19
#67
0&
1#
#72
b1 -
0'
03
#73
0*
06
#74
0!
#77
09
#87
b1 .
1,
18
#94
0)
05
#95
0;
#96
1%
0$
#116
0+
07
#117
1&
#122
1'
13
#123
0%
0<
#124
0"
#127
19
#128
0&
0#
#133
02
b0 -
0'
03
#134
1*
16
#135
1!
#138
09
#148
b10 .
0,
08
#155
1)
15
#156
1;
#157
1%
1$
#177
1+
17
#178
1&
#183
1(
14
#184
0%
1<
#185
1"
#195
0*
06
#196
0!
#198
1:
#199
0&
1#
#204
b1 -
0(
04
#216
0)
05
#217
0;
#219
0:
b11 .
1,
18
#220
1%
0$
#240
0+
07
#241
1&
#246
1(
14
#247
0%
0<
#248
0"
#258
1*
16
#259
1!
#261
1:
#262
0#
0&
#267
12
b0 -
0(
04
#279
1)
15
#280
1;
#282
0:
#312
b0 .
0,
08
#313
1%
1$
#333
1+
17
#334
1&
#339
1'
13
#340
0%
1<
#341
1"
#344
19
#345
0&
1#
#350
b1 -
0'
03
#351
0*
06
#352
0!
#355
09
#365
b1 .
1,
18
#372
0)
05
#373
0;
#374
1%
0$
#394
0+
07
#395
1&
#400
1'
13
#401
0%
0<
#402
0"
#405
19
#406
0&
0#
#411
02
b0 -
0'
03
#412
1*
16
#413
1!
#416
09
#426
b10 .
0,
08
#433
1)
15
#434
1;
#435
1%
1$
#455
1+
17
#456
1&
#461
1(
14
#462
0%
1<
#463
1"
#473
0*
06
#474
0!
#476
1:
#477
0&
1#
#482
b1 -
0(
04
#494
0)
05
#495
0;
#497
0:
b11 .
1,
18
#498
1%
0$
